setup.py
RPI_FeatureSelection_tools/IPCMBFeatSelector.py
RPI_FeatureSelection_tools/JMIFeatSelector.py
RPI_FeatureSelection_tools/RPI_FeatureSelection_tools.ctf
RPI_FeatureSelection_tools/STMBFeatSelector.py
RPI_FeatureSelection_tools/STMBPlusFeatSelector.py
RPI_FeatureSelection_tools/__init__.py
RPI_FeatureSelection_tools/base.py
RPI_FeatureSelection_tools/supervised_learning.py
RPI_FeatureSelection_tools.egg-info/PKG-INFO
RPI_FeatureSelection_tools.egg-info/SOURCES.txt
RPI_FeatureSelection_tools.egg-info/dependency_links.txt
RPI_FeatureSelection_tools.egg-info/top_level.txt