Metadata-Version: 1.0
Name: RPI-FeatureSelection-tools
Version: 1.0.0
Summary: RPI Feature Selection toolbox, the initial version with 4 primitives including the baseline methods
Home-page: https://www.ecse.rpi.edu/~cvrl/liuk
Author: Keyi Liu
Author-email: liuk7@rpi.edu
License: UNKNOWN
Platform: Linux
Platform: Windows
Platform: MacOS
